alabaster/__init__.py
alabaster/about.html
alabaster/donate.html
alabaster/layout.html
alabaster/navigation.html
alabaster/relations.html
alabaster/support.py
alabaster/theme.conf
alabaster/static/alabaster.css_t
alabaster/static/custom.css
alabaster-0.7.14.dist-info/entry_points.txt
alabaster-0.7.14.dist-info/WHEEL
alabaster-0.7.14.dist-info/METADATA
alabaster-0.7.14.dist-info/RECORD
