Metadata-Version: 2.1
Name: alabaster
Version: 0.7.14
Summary: A configurable sidebar-enabled Sphinx theme
Author-email: Jeff Forcier <jeff@bitprophet.org>
Maintainer: The Sphinx Developers
Requires-Python: >=3.9
Classifier: Development Status :: 5 - Production/Stable
Classifier: Framework :: Sphinx
Classifier: Framework :: Sphinx :: Theme
Classifier: Intended Audience :: Developers
Classifier: License :: OSI Approved :: BSD License
Classifier: Operating System :: OS Independent
Classifier: Programming Language :: Python :: 3
Classifier: Programming Language :: Python :: 3 :: Only
Classifier: Programming Language :: Python :: 3.9
Classifier: Programming Language :: Python :: 3.10
Classifier: Programming Language :: Python :: 3.11
Classifier: Programming Language :: Python :: 3.12
Classifier: Programming Language :: Python :: 3.13
Classifier: Programming Language :: Python :: Implementation :: CPython
Classifier: Programming Language :: Python :: Implementation :: PyPy
Classifier: Topic :: Documentation
Classifier: Topic :: Software Development :: Documentation
Project-URL: Changelog, https://alabaster.readthedocs.io/en/latest/changelog.html
Project-URL: Documentation, https://alabaster.readthedocs.io/
Project-URL: Download, https://pypi.org/project/alabaster/
Project-URL: Homepage, https://alabaster.readthedocs.io/
Project-URL: Issue tracker, https://github.com/bitprophet/alabaster/issues
Project-URL: Source, https://github.com/sphinx-doc/alabaster
